{
  "app-id": "re.sonny.Playhouse",
  "runtime": "org.gnome.Platform",
  "runtime-version": "43",
  "sdk": "org.gnome.Sdk",
  "command": "re.sonny.Playhouse",
  "finish-args": [
    "--share=ipc",
    "--socket=fallback-x11",
    "--socket=wayland",
    "--device=dri",
    "--share=network"
  ],
  "modules": [
    {
      "name": "blueprint",
      "buildsystem": "meson",
      "builddir": true,
      "sources": [
        {
          "type": "git",
          "url": "https://gitlab.gnome.org/jwestman/blueprint-compiler.git",
          "tag": "v0.4.0",
          "commit": "75a6d95988736ec0471d22ceb07579c0cedac2ad"
        }
      ]
    },
    {
      "name": "Playhouse",
      "buildsystem": "meson",
      "builddir": true,
      "sources": [
        {
          "type": "dir",
          "path": "."
        }
      ]
    }
  ]
}
